README.rst
setup.cfg
setup.py
pjon_python/__init__.py
pjon_python/async_client.py
pjon_python/base_client.py
pjon_python/sync_client.py
pjon_python.egg-info/PKG-INFO
pjon_python.egg-info/SOURCES.txt
pjon_python.egg-info/dependency_links.txt
pjon_python.egg-info/top_level.txt
pjon_python/protocol/__init__.py
pjon_python/protocol/pjon_protocol.py
pjon_python/protocol/pjon_protocol_constants.py
pjon_python/strategies/__init__.py
pjon_python/strategies/pjon_hwserial_strategy.py
pjon_python/utils/RedisConn.py
pjon_python/utils/__init__.py
pjon_python/utils/crc8.py
pjon_python/utils/fakeserial.py
pjon_python/utils/serial_utils.py