Metadata-Version: 1.1
Name: pjon-python
Version: 4.2.5
Summary: Python implementation of the PJON communication protocol.
Home-page: https://github.com/Girgitt/PJON-python
Author: Zbigniew Zasieczny
Author-email: z.zasieczny@gmail.com
License: UNKNOWN
Download-URL: https://github.com/Girgitt/PJON-python/tarball/4.2.5
Keywords: PJON,multimaster,serial,RS485,arduino
Platform: UNKNOWN
